LICENSE
MANIFEST.in
README.rst
setup.cfg
setup.py
neokami/__init__.py
neokami/src/__init__.py
neokami/src/__init__.pyc
neokami/src/Neokami/Base.py
neokami/src/Neokami/Base.pyc
neokami/src/Neokami/ImageAnalyser.py
neokami/src/Neokami/ImageAnalyser.pyc
neokami/src/Neokami/NeokamiRequest.py
neokami/src/Neokami/NeokamiRequest.pyc
neokami/src/Neokami/NeokamiResponse.py
neokami/src/Neokami/NeokamiResponse.pyc
neokami/src/Neokami/SentimentAnalyser.py
neokami/src/Neokami/SentimentAnalyser.pyc
neokami/src/Neokami/TopicDetection.py
neokami/src/Neokami/TopicDetection.pyc
neokami/src/Neokami/VisualCortex.py
neokami/src/Neokami/VisualCortex.pyc
neokami/src/Neokami/__init__.py
neokami/src/Neokami/__init__.pyc
neokami/src/Neokami/Exceptions/NeokamiAuthorizationException.py
neokami/src/Neokami/Exceptions/NeokamiAuthorizationException.pyc
neokami/src/Neokami/Exceptions/NeokamiBaseException.py
neokami/src/Neokami/Exceptions/NeokamiBaseException.pyc
neokami/src/Neokami/Exceptions/NeokamiBlockedException.py
neokami/src/Neokami/Exceptions/NeokamiBlockedException.pyc
neokami/src/Neokami/Exceptions/NeokamiParametersException.py
neokami/src/Neokami/Exceptions/NeokamiParametersException.pyc
neokami/src/Neokami/Exceptions/NeokamiResponseException.py
neokami/src/Neokami/Exceptions/NeokamiSDKException.py
neokami/src/Neokami/Exceptions/NeokamiSDKException.pyc
neokami/src/Neokami/Exceptions/NeokamiServerException.py
neokami/src/Neokami/Exceptions/NeokamiServerException.pyc
neokami/src/Neokami/Exceptions/__init__.py
neokami/src/Neokami/Exceptions/__init__.pyc
neokami/src/Neokami/HttpClients/NeokamiCurl.py
neokami/src/Neokami/HttpClients/NeokamiCurl.pyc
neokami/src/Neokami/HttpClients/__init__.py
neokami/src/Neokami/HttpClients/__init__.pyc
neokami/tests/NeokamiTestCredentials.py.replace
neokami/tests/NeokamiTestModel.py.replace
neokami/tests/__init__.py
neokami/tests/__init__.pyc
neokami/tests/test_neokami_exception.py
neokami/tests/test_neokami_image_request.py
neokami_sdk.egg-info/PKG-INFO
neokami_sdk.egg-info/SOURCES.txt
neokami_sdk.egg-info/dependency_links.txt
neokami_sdk.egg-info/requires.txt
neokami_sdk.egg-info/top_level.txt