Metadata-Version: 1.1
Name: neokami-sdk
Version: 0.2
Summary: Python sdk for Neokami API
Home-page: https://github.com/NeokamiCode/Python-SDK
Author: Neokami
Author-email: team@neokami.com
License: Apache Software License
Keywords: sdk,machine learning,neokami
Platform: UNKNOWN
Classifier: Development Status :: 5 - Production/Stable
Classifier: Intended Audience :: Developers
Classifier: Topic :: Scientific/Engineering :: Artificial Intelligence
Classifier: License :: OSI Approved :: Apache Software License
Classifier: Programming Language :: Python :: 2
Classifier: Programming Language :: Python :: 2.7
Classifier: Programming Language :: Python :: 3
Classifier: Programming Language :: Python :: 3.4
